Workbook

Sheet Dashboard
A1: PL/SQL Zero-to-Hero Progress Dashboard | B1: PL/SQL Zero-to-Hero Progress Dashboard | C1: PL/SQL Zero-to-Hero Progress Dashboard | D1: PL/SQL Zero-to-Hero Progress Dashboard | E1: PL/SQL Zero-to-Hero Progress Dashboard | F1: PL/SQL Zero-to-Hero Progress Dashboard | G1: PL/SQL Zero-to-Hero Progress Dashboard | H1: PL/SQL Zero-to-Hero Progress Dashboard | I1: PL/SQL Zero-to-Hero Progress Dashboard | J1: PL/SQL Zero-to-Hero Progress Dashboard | K1: PL/SQL Zero-to-Hero Progress Dashboard | L1: PL/SQL Zero-to-Hero Progress Dashboard
A2: PL/SQL Zero-to-Hero Progress Dashboard | B2: PL/SQL Zero-to-Hero Progress Dashboard | C2: PL/SQL Zero-to-Hero Progress Dashboard | D2: PL/SQL Zero-to-Hero Progress Dashboard | E2: PL/SQL Zero-to-Hero Progress Dashboard | F2: PL/SQL Zero-to-Hero Progress Dashboard | G2: PL/SQL Zero-to-Hero Progress Dashboard | H2: PL/SQL Zero-to-Hero Progress Dashboard | I2: PL/SQL Zero-to-Hero Progress Dashboard | J2: PL/SQL Zero-to-Hero Progress Dashboard | K2: PL/SQL Zero-to-Hero Progress Dashboard | L2: PL/SQL Zero-to-Hero Progress Dashboard
A3: Default plan: 26 weeks from 2026-07-20 at 8 hours per week. Change assumptions on Setup. | B3: Default plan: 26 weeks from 2026-07-20 at 8 hours per week. Change assumptions on Setup. | C3: Default plan: 26 weeks from 2026-07-20 at 8 hours per week. Change assumptions on Setup. | D3: Default plan: 26 weeks from 2026-07-20 at 8 hours per week. Change assumptions on Setup. | E3: Default plan: 26 weeks from 2026-07-20 at 8 hours per week. Change assumptions on Setup. | F3: Default plan: 26 weeks from 2026-07-20 at 8 hours per week. Change assumptions on Setup. | G3: Default plan: 26 weeks from 2026-07-20 at 8 hours per week. Change assumptions on Setup. | H3: Default plan: 26 weeks from 2026-07-20 at 8 hours per week. Change assumptions on Setup. | I3: Default plan: 26 weeks from 2026-07-20 at 8 hours per week. Change assumptions on Setup. | J3: Default plan: 26 weeks from 2026-07-20 at 8 hours per week. Change assumptions on Setup. | K3: Default plan: 26 weeks from 2026-07-20 at 8 hours per week. Change assumptions on Setup. | L3: Default plan: 26 weeks from 2026-07-20 at 8 hours per week. Change assumptions on Setup.
A5: Overall Progress | B5: Overall Progress | C5: Overall Progress | D5: Topics Completed | E5: Topics Completed | F5: Topics Completed | G5: Hours Logged | H5: Hours Logged | I5: Hours Logged | J5: Current Week | K5: Current Week | L5: Current Week
A6: =AVERAGE('Topic Checklist'!$I$5:$I$134) -> 0.00076923077 | D6: =COUNTIF('Topic Checklist'!$G$5:$G$134,"Completed") -> 0 | G6: =SUM('Practice Log'!$G$5:$G$204) -> 0 | J6: =MIN(Setup!$B$8,MAX(1,INT((TODAY()-Setup!$B$6)/7)+1)) -> 1
A9: Current Focus | B9: Current Focus | C9: Current Focus | D9: Current Focus | E9: Current Focus | F9: Current Focus | G9: Current Focus | H9: Current Focus | J9: Needs Attention | K9: Needs Attention | L9: Needs Attention
A10: Phase | C10: =INDEX('Weekly Tracker'!$D$5:$D$30,$J$6) -> Oracle SQL | J10: Overdue topics | L10: =COUNTIFS('Topic Checklist'!$G$5:$G$134,"<>Completed",'Topic Checklist'!$J$5:$J$134,"<"&TODAY()) -> 0
A11: Focus | C11: =INDEX('Weekly Tracker'!$E$5:$E$30,$J$6) -> Relational design and Oracle data types | J11: Blocked topics | L11: =COUNTIF('Topic Checklist'!$G$5:$G$134,"Blocked") -> 0
A12: Deliverable | C12: =INDEX('Weekly Tracker'!$F$5:$F$30,$J$6) -> Inventory ERD and normalized table plan | J12: Current hours variance | L12: =INDEX('Weekly Tracker'!$K$5:$K$30,$J$6) -> -8
A15: Phase | B15: Completion | C15: Topics Done | D15: Total Topics
A16: Oracle SQL | B16: =IFERROR(AVERAGEIF('Topic Checklist'!$C$5:$C$134,A16,'Topic Checklist'!$I$5:$I$134),0) -> 0.005 | C16: =COUNTIFS('Topic Checklist'!$C$5:$C$134,A16,'Topic Checklist'!$G$5:$G$134,"Completed") -> 0 | D16: =COUNTIF('Topic Checklist'!$C$5:$C$134,A16) -> 20
A17: PL/SQL Fundamentals | B17: =IFERROR(AVERAGEIF('Topic Checklist'!$C$5:$C$134,A17,'Topic Checklist'!$I$5:$I$134),0) -> 0 | C17: =COUNTIFS('Topic Checklist'!$C$5:$C$134,A17,'Topic Checklist'!$G$5:$G$134,"Completed") -> 0 | D17: =COUNTIF('Topic Checklist'!$C$5:$C$134,A17) -> 20
A18: Intermediate PL/SQL | B18: =IFERROR(AVERAGEIF('Topic Checklist'!$C$5:$C$134,A18,'Topic Checklist'!$I$5:$I$134),0) -> 0 | C18: =COUNTIFS('Topic Checklist'!$C$5:$C$134,A18,'Topic Checklist'!$G$5:$G$134,"Completed") -> 0 | D18: =COUNTIF('Topic Checklist'!$C$5:$C$134,A18) -> 20
A19: Enterprise PL/SQL | B19: =IFERROR(AVERAGEIF('Topic Checklist'!$C$5:$C$134,A19,'Topic Checklist'!$I$5:$I$134),0) -> 0 | C19: =COUNTIFS('Topic Checklist'!$C$5:$C$134,A19,'Topic Checklist'!$G$5:$G$134,"Completed") -> 0 | D19: =COUNTIF('Topic Checklist'!$C$5:$C$134,A19) -> 20
A20: Production PL/SQL | B20: =IFERROR(AVERAGEIF('Topic Checklist'!$C$5:$C$134,A20,'Topic Checklist'!$I$5:$I$134),0) -> 0 | C20: =COUNTIFS('Topic Checklist'!$C$5:$C$134,A20,'Topic Checklist'!$G$5:$G$134,"Completed") -> 0 | D20: =COUNTIF('Topic Checklist'!$C$5:$C$134,A20) -> 20
A21: APEX Integration | B21: =IFERROR(AVERAGEIF('Topic Checklist'!$C$5:$C$134,A21,'Topic Checklist'!$I$5:$I$134),0) -> 0 | C21: =COUNTIFS('Topic Checklist'!$C$5:$C$134,A21,'Topic Checklist'!$G$5:$G$134,"Completed") -> 0 | D21: =COUNTIF('Topic Checklist'!$C$5:$C$134,A21) -> 10
A22: Capstone | B22: =IFERROR(AVERAGEIF('Topic Checklist'!$C$5:$C$134,A22,'Topic Checklist'!$I$5:$I$134),0) -> 0 | C22: =COUNTIFS('Topic Checklist'!$C$5:$C$134,A22,'Topic Checklist'!$G$5:$G$134,"Completed") -> 0 | D22: =COUNTIF('Topic Checklist'!$C$5:$C$134,A22) -> 20
A26: Week | B26: Planned Hours | C26: Logged Hours
A27: 1 | B27: ='Weekly Tracker'!$G$5 -> 8 | C27: ='Weekly Tracker'!$H$5 -> 0
A28: 2 | B28: ='Weekly Tracker'!$G$6 -> 8 | C28: ='Weekly Tracker'!$H$6 -> 0
A29: 3 | B29: ='Weekly Tracker'!$G$7 -> 8 | C29: ='Weekly Tracker'!$H$7 -> 0
A30: 4 | B30: ='Weekly Tracker'!$G$8 -> 8 | C30: ='Weekly Tracker'!$H$8 -> 0
A31: 5 | B31: ='Weekly Tracker'!$G$9 -> 8 | C31: ='Weekly Tracker'!$H$9 -> 0
A32: 6 | B32: ='Weekly Tracker'!$G$10 -> 8 | C32: ='Weekly Tracker'!$H$10 -> 0
A33: 7 | B33: ='Weekly Tracker'!$G$11 -> 8 | C33: ='Weekly Tracker'!$H$11 -> 0
A34: 8 | B34: ='Weekly Tracker'!$G$12 -> 8 | C34: ='Weekly Tracker'!$H$12 -> 0
A35: 9 | B35: ='Weekly Tracker'!$G$13 -> 8 | C35: ='Weekly Tracker'!$H$13 -> 0
A36: 10 | B36: ='Weekly Tracker'!$G$14 -> 8 | C36: ='Weekly Tracker'!$H$14 -> 0
A37: 11 | B37: ='Weekly Tracker'!$G$15 -> 8 | C37: ='Weekly Tracker'!$H$15 -> 0
A38: 12 | B38: ='Weekly Tracker'!$G$16 -> 8 | C38: ='Weekly Tracker'!$H$16 -> 0
A39: 13 | B39: ='Weekly Tracker'!$G$17 -> 8 | C39: ='Weekly Tracker'!$H$17 -> 0
A40: 14 | B40: ='Weekly Tracker'!$G$18 -> 8 | C40: ='Weekly Tracker'!$H$18 -> 0
A41: 15 | B41: ='Weekly Tracker'!$G$19 -> 8 | C41: ='Weekly Tracker'!$H$19 -> 0
A42: 16 | B42: ='Weekly Tracker'!$G$20 -> 8 | C42: ='Weekly Tracker'!$H$20 -> 0
A43: 17 | B43: ='Weekly Tracker'!$G$21 -> 8 | C43: ='Weekly Tracker'!$H$21 -> 0
A44: 18 | B44: ='Weekly Tracker'!$G$22 -> 8 | C44: ='Weekly Tracker'!$H$22 -> 0
A45: 19 | B45: ='Weekly Tracker'!$G$23 -> 8 | C45: ='Weekly Tracker'!$H$23 -> 0
A46: 20 | B46: ='Weekly Tracker'!$G$24 -> 8 | C46: ='Weekly Tracker'!$H$24 -> 0
A47: 21 | B47: ='Weekly Tracker'!$G$25 -> 8 | C47: ='Weekly Tracker'!$H$25 -> 0
A48: 22 | B48: ='Weekly Tracker'!$G$26 -> 8 | C48: ='Weekly Tracker'!$H$26 -> 0
A49: 23 | B49: ='Weekly Tracker'!$G$27 -> 8 | C49: ='Weekly Tracker'!$H$27 -> 0
A50: 24 | B50: ='Weekly Tracker'!$G$28 -> 8 | C50: ='Weekly Tracker'!$H$28 -> 0
A51: 25 | B51: ='Weekly Tracker'!$G$29 -> 8 | C51: ='Weekly Tracker'!$H$29 -> 0
A52: 26 | B52: ='Weekly Tracker'!$G$30 -> 8 | C52: ='Weekly Tracker'!$H$30 -> 0
A55: How to use this tracker | B55: How to use this tracker | C55: How to use this tracker | D55: How to use this tracker | E55: How to use this tracker | F55: How to use this tracker | G55: How to use this tracker | H55: How to use this tracker | I55: How to use this tracker | J55: How to use this tracker | K55: How to use this tracker | L55: How to use this tracker
A56: 1) Change start date or weekly target on Setup. 2) Update each Topic Checklist status and attach evidence. 3) Record every study session in Practice Log. 4) Review Weekly Tracker and Milestones at the end of each week. 5) Use Capstone as your final portfolio definition of done. | B56: 1) Change start date or weekly target on Setup. 2) Update each Topic Checklist status and attach evidence. 3) Record every study session in Practice Log. 4) Review Weekly Tracker and Milestones at the end of each week. 5) Use Capstone as your final portfolio definition of done. | C56: 1) Change start date or weekly target on Setup. 2) Update each Topic Checklist status and attach evidence. 3) Record every study session in Practice Log. 4) Review Weekly Tracker and Milestones at the end of each week. 5) Use Capstone as your final portfolio definition of done. | D56: 1) Change start date or weekly target on Setup. 2) Update each Topic Checklist status and attach evidence. 3) Record every study session in Practice Log. 4) Review Weekly Tracker and Milestones at the end of each week. 5) Use Capstone as your final portfolio definition of done. | E56: 1) Change start date or weekly target on Setup. 2) Update each Topic Checklist status and attach evidence. 3) Record every study session in Practice Log. 4) Review Weekly Tracker and Milestones at the end of each week. 5) Use Capstone as your final portfolio definition of done. | F56: 1) Change start date or weekly target on Setup. 2) Update each Topic Checklist status and attach evidence. 3) Record every study session in Practice Log. 4) Review Weekly Tracker and Milestones at the end of each week. 5) Use Capstone as your final portfolio definition of done. | G56: 1) Change start date or weekly target on Setup. 2) Update each Topic Checklist status and attach evidence. 3) Record every study session in Practice Log. 4) Review Weekly Tracker and Milestones at the end of each week. 5) Use Capstone as your final portfolio definition of done. | H56: 1) Change start date or weekly target on Setup. 2) Update each Topic Checklist status and attach evidence. 3) Record every study session in Practice Log. 4) Review Weekly Tracker and Milestones at the end of each week. 5) Use Capstone as your final portfolio definition of done. | I56: 1) Change start date or weekly target on Setup. 2) Update each Topic Checklist status and attach evidence. 3) Record every study session in Practice Log. 4) Review Weekly Tracker and Milestones at the end of each week. 5) Use Capstone as your final portfolio definition of done. | J56: 1) Change start date or weekly target on Setup. 2) Update each Topic Checklist status and attach evidence. 3) Record every study session in Practice Log. 4) Review Weekly Tracker and Milestones at the end of each week. 5) Use Capstone as your final portfolio definition of done. | K56: 1) Change start date or weekly target on Setup. 2) Update each Topic Checklist status and attach evidence. 3) Record every study session in Practice Log. 4) Review Weekly Tracker and Milestones at the end of each week. 5) Use Capstone as your final portfolio definition of done. | L56: 1) Change start date or weekly target on Setup. 2) Update each Topic Checklist status and attach evidence. 3) Record every study session in Practice Log. 4) Review Weekly Tracker and Milestones at the end of each week. 5) Use Capstone as your final portfolio definition of done.
A57: 1) Change start date or weekly target on Setup. 2) Update each Topic Checklist status and attach evidence. 3) Record every study session in Practice Log. 4) Review Weekly Tracker and Milestones at the end of each week. 5) Use Capstone as your final portfolio definition of done. | B57: 1) Change start date or weekly target on Setup. 2) Update each Topic Checklist status and attach evidence. 3) Record every study session in Practice Log. 4) Review Weekly Tracker and Milestones at the end of each week. 5) Use Capstone as your final portfolio definition of done. | C57: 1) Change start date or weekly target on Setup. 2) Update each Topic Checklist status and attach evidence. 3) Record every study session in Practice Log. 4) Review Weekly Tracker and Milestones at the end of each week. 5) Use Capstone as your final portfolio definition of done. | D57: 1) Change start date or weekly target on Setup. 2) Update each Topic Checklist status and attach evidence. 3) Record every study session in Practice Log. 4) Review Weekly Tracker and Milestones at the end of each week. 5) Use Capstone as your final portfolio definition of done. | E57: 1) Change start date or weekly target on Setup. 2) Update each Topic Checklist status and attach evidence. 3) Record every study session in Practice Log. 4) Review Weekly Tracker and Milestones at the end of each week. 5) Use Capstone as your final portfolio definition of done. | F57: 1) Change start date or weekly target on Setup. 2) Update each Topic Checklist status and attach evidence. 3) Record every study session in Practice Log. 4) Review Weekly Tracker and Milestones at the end of each week. 5) Use Capstone as your final portfolio definition of done. | G57: 1) Change start date or weekly target on Setup. 2) Update each Topic Checklist status and attach evidence. 3) Record every study session in Practice Log. 4) Review Weekly Tracker and Milestones at the end of each week. 5) Use Capstone as your final portfolio definition of done. | H57: 1) Change start date or weekly target on Setup. 2) Update each Topic Checklist status and attach evidence. 3) Record every study session in Practice Log. 4) Review Weekly Tracker and Milestones at the end of each week. 5) Use Capstone as your final portfolio definition of done. | I57: 1) Change start date or weekly target on Setup. 2) Update each Topic Checklist status and attach evidence. 3) Record every study session in Practice Log. 4) Review Weekly Tracker and Milestones at the end of each week. 5) Use Capstone as your final portfolio definition of done. | J57: 1) Change start date or weekly target on Setup. 2) Update each Topic Checklist status and attach evidence. 3) Record every study session in Practice Log. 4) Review Weekly Tracker and Milestones at the end of each week. 5) Use Capstone as your final portfolio definition of done. | K57: 1) Change start date or weekly target on Setup. 2) Update each Topic Checklist status and attach evidence. 3) Record every study session in Practice Log. 4) Review Weekly Tracker and Milestones at the end of each week. 5) Use Capstone as your final portfolio definition of done. | L57: 1) Change start date or weekly target on Setup. 2) Update each Topic Checklist status and attach evidence. 3) Record every study session in Practice Log. 4) Review Weekly Tracker and Milestones at the end of each week. 5) Use Capstone as your final portfolio definition of done.
A58: 1) Change start date or weekly target on Setup. 2) Update each Topic Checklist status and attach evidence. 3) Record every study session in Practice Log. 4) Review Weekly Tracker and Milestones at the end of each week. 5) Use Capstone as your final portfolio definition of done. | B58: 1) Change start date or weekly target on Setup. 2) Update each Topic Checklist status and attach evidence. 3) Record every study session in Practice Log. 4) Review Weekly Tracker and Milestones at the end of each week. 5) Use Capstone as your final portfolio definition of done. | C58: 1) Change start date or weekly target on Setup. 2) Update each Topic Checklist status and attach evidence. 3) Record every study session in Practice Log. 4) Review Weekly Tracker and Milestones at the end of each week. 5) Use Capstone as your final portfolio definition of done. | D58: 1) Change start date or weekly target on Setup. 2) Update each Topic Checklist status and attach evidence. 3) Record every study session in Practice Log. 4) Review Weekly Tracker and Milestones at the end of each week. 5) Use Capstone as your final portfolio definition of done. | E58: 1) Change start date or weekly target on Setup. 2) Update each Topic Checklist status and attach evidence. 3) Record every study session in Practice Log. 4) Review Weekly Tracker and Milestones at the end of each week. 5) Use Capstone as your final portfolio definition of done. | F58: 1) Change start date or weekly target on Setup. 2) Update each Topic Checklist status and attach evidence. 3) Record every study session in Practice Log. 4) Review Weekly Tracker and Milestones at the end of each week. 5) Use Capstone as your final portfolio definition of done. | G58: 1) Change start date or weekly target on Setup. 2) Update each Topic Checklist status and attach evidence. 3) Record every study session in Practice Log. 4) Review Weekly Tracker and Milestones at the end of each week. 5) Use Capstone as your final portfolio definition of done. | H58: 1) Change start date or weekly target on Setup. 2) Update each Topic Checklist status and attach evidence. 3) Record every study session in Practice Log. 4) Review Weekly Tracker and Milestones at the end of each week. 5) Use Capstone as your final portfolio definition of done. | I58: 1) Change start date or weekly target on Setup. 2) Update each Topic Checklist status and attach evidence. 3) Record every study session in Practice Log. 4) Review Weekly Tracker and Milestones at the end of each week. 5) Use Capstone as your final portfolio definition of done. | J58: 1) Change start date or weekly target on Setup. 2) Update each Topic Checklist status and attach evidence. 3) Record every study session in Practice Log. 4) Review Weekly Tracker and Milestones at the end of each week. 5) Use Capstone as your final portfolio definition of done. | K58: 1) Change start date or weekly target on Setup. 2) Update each Topic Checklist status and attach evidence. 3) Record every study session in Practice Log. 4) Review Weekly Tracker and Milestones at the end of each week. 5) Use Capstone as your final portfolio definition of done. | L58: 1) Change start date or weekly target on Setup. 2) Update each Topic Checklist status and attach evidence. 3) Record every study session in Practice Log. 4) Review Weekly Tracker and Milestones at the end of each week. 5) Use Capstone as your final portfolio definition of done.

Sheet Weekly Tracker
A1: 26-Week PL/SQL & Oracle APEX Roadmap | B1: 26-Week PL/SQL & Oracle APEX Roadmap | C1: 26-Week PL/SQL & Oracle APEX Roadmap | D1: 26-Week PL/SQL & Oracle APEX Roadmap | E1: 26-Week PL/SQL & Oracle APEX Roadmap | F1: 26-Week PL/SQL & Oracle APEX Roadmap | G1: 26-Week PL/SQL & Oracle APEX Roadmap | H1: 26-Week PL/SQL & Oracle APEX Roadmap | I1: 26-Week PL/SQL & Oracle APEX Roadmap | J1: 26-Week PL/SQL & Oracle APEX Roadmap | K1: 26-Week PL/SQL & Oracle APEX Roadmap | L1: 26-Week PL/SQL & Oracle APEX Roadmap
A2: 26-Week PL/SQL & Oracle APEX Roadmap | B2: 26-Week PL/SQL & Oracle APEX Roadmap | C2: 26-Week PL/SQL & Oracle APEX Roadmap | D2: 26-Week PL/SQL & Oracle APEX Roadmap | E2: 26-Week PL/SQL & Oracle APEX Roadmap | F2: 26-Week PL/SQL & Oracle APEX Roadmap | G2: 26-Week PL/SQL & Oracle APEX Roadmap | H2: 26-Week PL/SQL & Oracle APEX Roadmap | I2: 26-Week PL/SQL & Oracle APEX Roadmap | J2: 26-Week PL/SQL & Oracle APEX Roadmap | K2: 26-Week PL/SQL & Oracle APEX Roadmap | L2: 26-Week PL/SQL & Oracle APEX Roadmap
A3: Weekly completion and actual hours are calculated from the Topic Checklist and Practice Log. | B3: Weekly completion and actual hours are calculated from the Topic Checklist and Practice Log. | C3: Weekly completion and actual hours are calculated from the Topic Checklist and Practice Log. | D3: Weekly completion and actual hours are calculated from the Topic Checklist and Practice Log. | E3: Weekly completion and actual hours are calculated from the Topic Checklist and Practice Log. | F3: Weekly completion and actual hours are calculated from the Topic Checklist and Practice Log. | G3: Weekly completion and actual hours are calculated from the Topic Checklist and Practice Log. | H3: Weekly completion and actual hours are calculated from the Topic Checklist and Practice Log. | I3: Weekly completion and actual hours are calculated from the Topic Checklist and Practice Log. | J3: Weekly completion and actual hours are calculated from the Topic Checklist and Practice Log. | K3: Weekly completion and actual hours are calculated from the Topic Checklist and Practice Log. | L3: Weekly completion and actual hours are calculated from the Topic Checklist and Practice Log.
A4: Week | B4: Start | C4: End | D4: Phase | E4: Weekly Focus | F4: Exit Deliverable | G4: Planned Hours | H4: Actual Hours | I4: Status | J4: Topic Completion | K4: Hours Variance | L4: Weekly Review Notes
A5: 1 | B5: =Setup!$B$6+7*(A5-1) -> 46223 | C5: =B5+6 -> 46229 | D5: Oracle SQL | E5: Relational design and Oracle data types | F5: Inventory ERD and normalized table plan | G5: =Setup!$B$7 -> 8 | H5: =SUMIF('Practice Log'!$B$5:$B$204,A5,'Practice Log'!$G$5:$G$204) -> 0 | I5: =IF(J5=1,"Completed",IF(TODAY()<B5,"Upcoming",IF(TODAY()<=C5,"Active","Behind"))) -> Upcoming | J5: =IFERROR(AVERAGEIF('Topic Checklist'!$B$5:$B$134,A5,'Topic Checklist'!$I$5:$I$134),0) -> 0.02 | K5: =H5-G5 -> -8
A6: 2 | B6: =Setup!$B$6+7*(A6-1) -> 46230 | C6: =B6+6 -> 46236 | D6: Oracle SQL | E6: SELECT, filtering and Oracle functions | F6: Twenty accurate single-table queries | G6: =Setup!$B$7 -> 8 | H6: =SUMIF('Practice Log'!$B$5:$B$204,A6,'Practice Log'!$G$5:$G$204) -> 0 | I6: =IF(J6=1,"Completed",IF(TODAY()<B6,"Upcoming",IF(TODAY()<=C6,"Active","Behind"))) -> Upcoming | J6: =IFERROR(AVERAGEIF('Topic Checklist'!$B$5:$B$134,A6,'Topic Checklist'!$I$5:$I$134),0) -> 0 | K6: =H6-G6 -> -8
A7: 3 | B7: =Setup!$B$6+7*(A7-1) -> 46237 | C7: =B7+6 -> 46243 | D7: Oracle SQL | E7: Joins, aggregation and subqueries | F7: Sales and inventory reporting query set | G7: =Setup!$B$7 -> 8 | H7: =SUMIF('Practice Log'!$B$5:$B$204,A7,'Practice Log'!$G$5:$G$204) -> 0 | I7: =IF(J7=1,"Completed",IF(TODAY()<B7,"Upcoming",IF(TODAY()<=C7,"Active","Behind"))) -> Upcoming | J7: =IFERROR(AVERAGEIF('Topic Checklist'!$B$5:$B$134,A7,'Topic Checklist'!$I$5:$I$134),0) -> 0 | K7: =H7-G7 -> -8
A8: 4 | B8: =Setup!$B$6+7*(A8-1) -> 46244 | C8: =B8+6 -> 46250 | D8: Oracle SQL | E8: DDL, DML, transactions and advanced SQL | F8: Working schema plus 40-query checkpoint | G8: =Setup!$B$7 -> 8 | H8: =SUMIF('Practice Log'!$B$5:$B$204,A8,'Practice Log'!$G$5:$G$204) -> 0 | I8: =IF(J8=1,"Completed",IF(TODAY()<B8,"Upcoming",IF(TODAY()<=C8,"Active","Behind"))) -> Upcoming | J8: =IFERROR(AVERAGEIF('Topic Checklist'!$B$5:$B$134,A8,'Topic Checklist'!$I$5:$I$134),0) -> 0 | K8: =H8-G8 -> -8
A9: 5 | B9: =Setup!$B$6+7*(A9-1) -> 46251 | C9: =B9+6 -> 46257 | D9: PL/SQL Fundamentals | E9: PL/SQL blocks, variables and anchored types | F9: Anonymous blocks that safely read and calculate data | G9: =Setup!$B$7 -> 8 | H9: =SUMIF('Practice Log'!$B$5:$B$204,A9,'Practice Log'!$G$5:$G$204) -> 0 | I9: =IF(J9=1,"Completed",IF(TODAY()<B9,"Upcoming",IF(TODAY()<=C9,"Active","Behind"))) -> Upcoming | J9: =IFERROR(AVERAGEIF('Topic Checklist'!$B$5:$B$134,A9,'Topic Checklist'!$I$5:$I$134),0) -> 0 | K9: =H9-G9 -> -8
A10: 6 | B10: =Setup!$B$6+7*(A10-1) -> 46258 | C10: =B10+6 -> 46264 | D10: PL/SQL Fundamentals | E10: Control flow and local logic | F10: Validated calculation and decision blocks | G10: =Setup!$B$7 -> 8 | H10: =SUMIF('Practice Log'!$B$5:$B$204,A10,'Practice Log'!$G$5:$G$204) -> 0 | I10: =IF(J10=1,"Completed",IF(TODAY()<B10,"Upcoming",IF(TODAY()<=C10,"Active","Behind"))) -> Upcoming | J10: =IFERROR(AVERAGEIF('Topic Checklist'!$B$5:$B$134,A10,'Topic Checklist'!$I$5:$I$134),0) -> 0 | K10: =H10-G10 -> -8
A11: 7 | B11: =Setup!$B$6+7*(A11-1) -> 46265 | C11: =B11+6 -> 46271 | D11: PL/SQL Fundamentals | E11: SQL inside PL/SQL and transaction control | F11: Safe stock-update transaction | G11: =Setup!$B$7 -> 8 | H11: =SUMIF('Practice Log'!$B$5:$B$204,A11,'Practice Log'!$G$5:$G$204) -> 0 | I11: =IF(J11=1,"Completed",IF(TODAY()<B11,"Upcoming",IF(TODAY()<=C11,"Active","Behind"))) -> Upcoming | J11: =IFERROR(AVERAGEIF('Topic Checklist'!$B$5:$B$134,A11,'Topic Checklist'!$I$5:$I$134),0) -> 0 | K11: =H11-G11 -> -8
A12: 8 | B12: =Setup!$B$6+7*(A12-1) -> 46272 | C12: =B12+6 -> 46278 | D12: PL/SQL Fundamentals | E12: Procedures, functions and exceptions | F12: Reusable order-calculation module | G12: =Setup!$B$7 -> 8 | H12: =SUMIF('Practice Log'!$B$5:$B$204,A12,'Practice Log'!$G$5:$G$204) -> 0 | I12: =IF(J12=1,"Completed",IF(TODAY()<B12,"Upcoming",IF(TODAY()<=C12,"Active","Behind"))) -> Upcoming | J12: =IFERROR(AVERAGEIF('Topic Checklist'!$B$5:$B$134,A12,'Topic Checklist'!$I$5:$I$134),0) -> 0 | K12: =H12-G12 -> -8
A13: 9 | B13: =Setup!$B$6+7*(A13-1) -> 46279 | C13: =B13+6 -> 46285 | D13: Intermediate PL/SQL | E13: Advanced cursors and records | F13: Cursor-driven reporting procedure | G13: =Setup!$B$7 -> 8 | H13: =SUMIF('Practice Log'!$B$5:$B$204,A13,'Practice Log'!$G$5:$G$204) -> 0 | I13: =IF(J13=1,"Completed",IF(TODAY()<B13,"Upcoming",IF(TODAY()<=C13,"Active","Behind"))) -> Upcoming | J13: =IFERROR(AVERAGEIF('Topic Checklist'!$B$5:$B$134,A13,'Topic Checklist'!$I$5:$I$134),0) -> 0 | K13: =H13-G13 -> -8
A14: 10 | B14: =Setup!$B$6+7*(A14-1) -> 46286 | C14: =B14+6 -> 46292 | D14: Intermediate PL/SQL | E14: Collections and in-memory processing | F14: Collection-based data transformation | G14: =Setup!$B$7 -> 8 | H14: =SUMIF('Practice Log'!$B$5:$B$204,A14,'Practice Log'!$G$5:$G$204) -> 0 | I14: =IF(J14=1,"Completed",IF(TODAY()<B14,"Upcoming",IF(TODAY()<=C14,"Active","Behind"))) -> Upcoming | J14: =IFERROR(AVERAGEIF('Topic Checklist'!$B$5:$B$134,A14,'Topic Checklist'!$I$5:$I$134),0) -> 0 | K14: =H14-G14 -> -8
A15: 11 | B15: =Setup!$B$6+7*(A15-1) -> 46293 | C15: =B15+6 -> 46299 | D15: Intermediate PL/SQL | E15: Package architecture | F15: order_api package specification and body | G15: =Setup!$B$7 -> 8 | H15: =SUMIF('Practice Log'!$B$5:$B$204,A15,'Practice Log'!$G$5:$G$204) -> 0 | I15: =IF(J15=1,"Completed",IF(TODAY()<B15,"Upcoming",IF(TODAY()<=C15,"Active","Behind"))) -> Upcoming | J15: =IFERROR(AVERAGEIF('Topic Checklist'!$B$5:$B$134,A15,'Topic Checklist'!$I$5:$I$134),0) -> 0 | K15: =H15-G15 -> -8
A16: 12 | B16: =Setup!$B$6+7*(A16-1) -> 46300 | C16: =B16+6 -> 46306 | D16: Intermediate PL/SQL | E16: Triggers and error architecture | F16: Audited package API with structured errors | G16: =Setup!$B$7 -> 8 | H16: =SUMIF('Practice Log'!$B$5:$B$204,A16,'Practice Log'!$G$5:$G$204) -> 0 | I16: =IF(J16=1,"Completed",IF(TODAY()<B16,"Upcoming",IF(TODAY()<=C16,"Active","Behind"))) -> Upcoming | J16: =IFERROR(AVERAGEIF('Topic Checklist'!$B$5:$B$134,A16,'Topic Checklist'!$I$5:$I$134),0) -> 0 | K16: =H16-G16 -> -8
... A30: 26 | B30: =Setup!$B$6+7*(A30-1) -> 46398 | C30: =B30+6 -> 46404 | D30: Capstone | E30: Hardening, documentation and demonstration | F30: Portfolio-ready application and repository | G30: =Setup!$B$7 -> 8 | H30: =SUMIF('Practice Log'!$B$5:$B$204,A30,'Practice Log'!$G$5:$G$204) -> 0 | I30: =IF(J30=1,"Completed",IF(TODAY()<B30,"Upcoming",IF(TODAY()<=C30,"Active","Behind"))) -> Upcoming | J30: =IFERROR(AVERAGEIF('Topic Checklist'!$B$5:$B$134,A30,'Topic Checklist'!$I$5:$I$134),0) -> 0 | K30: =H30-G30 -> -8

Sheet Topic Checklist
A1: Topic Checklist | B1: Topic Checklist | C1: Topic Checklist | D1: Topic Checklist | E1: Topic Checklist | F1: Topic Checklist | G1: Topic Checklist | H1: Topic Checklist | I1: Topic Checklist | J1: Topic Checklist | K1: Topic Checklist
A2: Topic Checklist | B2: Topic Checklist | C2: Topic Checklist | D2: Topic Checklist | E2: Topic Checklist | F2: Topic Checklist | G2: Topic Checklist | H2: Topic Checklist | I2: Topic Checklist | J2: Topic Checklist | K2: Topic Checklist
A3: Update Status and add evidence. Weekly and dashboard progress recalculate from these rows. | B3: Update Status and add evidence. Weekly and dashboard progress recalculate from these rows. | C3: Update Status and add evidence. Weekly and dashboard progress recalculate from these rows. | D3: Update Status and add evidence. Weekly and dashboard progress recalculate from these rows. | E3: Update Status and add evidence. Weekly and dashboard progress recalculate from these rows. | F3: Update Status and add evidence. Weekly and dashboard progress recalculate from these rows. | G3: Update Status and add evidence. Weekly and dashboard progress recalculate from these rows. | H3: Update Status and add evidence. Weekly and dashboard progress recalculate from these rows. | I3: Update Status and add evidence. Weekly and dashboard progress recalculate from these rows. | J3: Update Status and add evidence. Weekly and dashboard progress recalculate from these rows. | K3: Update Status and add evidence. Weekly and dashboard progress recalculate from these rows.
A4: ID | B4: Week | C4: Phase | D4: Topic | E4: Practical Evidence | F4: Priority | G4: Status | H4: Evidence / Link | I4: Completion | J4: Due Date | K4: Notes
A5: T001 | B5: 1 | C5: Oracle SQL | D5: Relational concepts, keys and cardinality | E5: Model one-to-many and many-to-many relationships | F5: Core | G5: In Progress | I5: 0.1 | J5: =Setup!$B$6+(B5*7)-1 -> 46229
A6: T002 | B6: 1 | C6: Oracle SQL | D6: Normalization through 3NF | E6: Normalize a raw inventory spreadsheet into related tables | F6: Core | G6: Not Started | I6: =IF(G6="Completed",1,IF(G6="In Progress",0.5,IF(G6="Blocked",0.25,0))) -> 0 | J6: =Setup!$B$6+(B6*7)-1 -> 46229
A7: T003 | B7: 1 | C7: Oracle SQL | D7: Oracle schema objects | E7: Identify tables, views, indexes, sequences and packages | F7: Core | G7: Not Started | I7: =IF(G7="Completed",1,IF(G7="In Progress",0.5,IF(G7="Blocked",0.25,0))) -> 0 | J7: =Setup!$B$6+(B7*7)-1 -> 46229
A8: T004 | B8: 1 | C8: Oracle SQL | D8: Oracle data types and NULL | E8: Choose correct types for inventory and orders | F8: Core | G8: Not Started | I8: =IF(G8="Completed",1,IF(G8="In Progress",0.5,IF(G8="Blocked",0.25,0))) -> 0 | J8: =Setup!$B$6+(B8*7)-1 -> 46229
A9: T005 | B9: 1 | C9: Oracle SQL | D9: ERD design | E9: Draw the first inventory and order ERD | F9: Core | G9: Not Started | I9: =IF(G9="Completed",1,IF(G9="In Progress",0.5,IF(G9="Blocked",0.25,0))) -> 0 | J9: =Setup!$B$6+(B9*7)-1 -> 46229
A10: T006 | B10: 2 | C10: Oracle SQL | D10: SELECT, aliases and expressions | E10: Write readable projection queries with aliases | F10: Core | G10: Not Started | I10: =IF(G10="Completed",1,IF(G10="In Progress",0.5,IF(G10="Blocked",0.25,0))) -> 0 | J10: =Setup!$B$6+(B10*7)-1 -> 46236
A11: T007 | B11: 2 | C11: Oracle SQL | D11: WHERE predicates and NULL logic | E11: Test comparison, range, list and null predicates | F11: Core | G11: Not Started | I11: =IF(G11="Completed",1,IF(G11="In Progress",0.5,IF(G11="Blocked",0.25,0))) -> 0 | J11: =Setup!$B$6+(B11*7)-1 -> 46236
A12: T008 | B12: 2 | C12: Oracle SQL | D12: String, number and date functions | E12: Create formatted customer and order outputs | F12: Core | G12: Not Started | I12: =IF(G12="Completed",1,IF(G12="In Progress",0.5,IF(G12="Blocked",0.25,0))) -> 0 | J12: =Setup!$B$6+(B12*7)-1 -> 46236
A13: T009 | B13: 2 | C13: Oracle SQL | D13: CASE, NVL, COALESCE and NULLIF | E13: Convert raw values into business-friendly labels | F13: Core | G13: Not Started | I13: =IF(G13="Completed",1,IF(G13="In Progress",0.5,IF(G13="Blocked",0.25,0))) -> 0 | J13: =Setup!$B$6+(B13*7)-1 -> 46236
A14: T010 | B14: 2 | C14: Oracle SQL | D14: Ordering and row limiting | E14: Produce deterministic top-N reports | F14: Important | G14: Not Started | I14: =IF(G14="Completed",1,IF(G14="In Progress",0.5,IF(G14="Blocked",0.25,0))) -> 0 | J14: =Setup!$B$6+(B14*7)-1 -> 46236
A15: T011 | B15: 3 | C15: Oracle SQL | D15: Inner, outer and self joins | E15: Join products, suppliers, orders and employees | F15: Core | G15: Not Started | I15: =IF(G15="Completed",1,IF(G15="In Progress",0.5,IF(G15="Blocked",0.25,0))) -> 0 | J15: =Setup!$B$6+(B15*7)-1 -> 46243
A16: T012 | B16: 3 | C16: Oracle SQL | D16: Aggregates, GROUP BY and HAVING | E16: Calculate revenue and stock totals | F16: Core | G16: Not Started | I16: =IF(G16="Completed",1,IF(G16="In Progress",0.5,IF(G16="Blocked",0.25,0))) -> 0 | J16: =Setup!$B$6+(B16*7)-1 -> 46243
A17: T013 | B17: 3 | C17: Oracle SQL | D17: Subqueries and correlated subqueries | E17: Find customers above their regional average | F17: Core | G17: Not Started | I17: =IF(G17="Completed",1,IF(G17="In Progress",0.5,IF(G17="Blocked",0.25,0))) -> 0 | J17: =Setup!$B$6+(B17*7)-1 -> 46243
... A134: T130 | B134: 26 | C134: Capstone | D134: Documentation and portfolio demo | E134: Publish ERD, README, screenshots and demo story | F134: Core | G134: Not Started | I134: =IF(G134="Completed",1,IF(G134="In Progress",0.5,IF(G134="Blocked",0.25,0))) -> 0 | J134: =Setup!$B$6+(B134*7)-1 -> 46404

Sheet Practice Log
A1: Practice Log | B1: Practice Log | C1: Practice Log | D1: Practice Log | E1: Practice Log | F1: Practice Log | G1: Practice Log | H1: Practice Log | I1: Practice Log | J1: Practice Log
A2: Practice Log | B2: Practice Log | C2: Practice Log | D2: Practice Log | E2: Practice Log | F2: Practice Log | G2: Practice Log | H2: Practice Log | I2: Practice Log | J2: Practice Log
A3: Add one row for every study, coding, debugging or review session. Week and hours calculate automatically. | B3: Add one row for every study, coding, debugging or review session. Week and hours calculate automatically. | C3: Add one row for every study, coding, debugging or review session. Week and hours calculate automatically. | D3: Add one row for every study, coding, debugging or review session. Week and hours calculate automatically. | E3: Add one row for every study, coding, debugging or review session. Week and hours calculate automatically. | F3: Add one row for every study, coding, debugging or review session. Week and hours calculate automatically. | G3: Add one row for every study, coding, debugging or review session. Week and hours calculate automatically. | H3: Add one row for every study, coding, debugging or review session. Week and hours calculate automatically. | I3: Add one row for every study, coding, debugging or review session. Week and hours calculate automatically. | J3: Add one row for every study, coding, debugging or review session. Week and hours calculate automatically.
A4: Date | B4: Week | C4: Session Type | D4: Topic | E4: What I Did | F4: Minutes | G4: Hours | H4: Result | I4: Evidence / Link | J4: Lesson or Blocker
B5: =IF(A5="","",MAX(1,MIN(Setup!$B$8,INT((A5-Setup!$B$6)/7)+1))) | G5: =IF(F5="","",F5/60)
B6: =IF(A6="","",MAX(1,MIN(Setup!$B$8,INT((A6-Setup!$B$6)/7)+1))) | G6: =IF(F6="","",F6/60)
B7: =IF(A7="","",MAX(1,MIN(Setup!$B$8,INT((A7-Setup!$B$6)/7)+1))) | G7: =IF(F7="","",F7/60)
B8: =IF(A8="","",MAX(1,MIN(Setup!$B$8,INT((A8-Setup!$B$6)/7)+1))) | G8: =IF(F8="","",F8/60)
B9: =IF(A9="","",MAX(1,MIN(Setup!$B$8,INT((A9-Setup!$B$6)/7)+1))) | G9: =IF(F9="","",F9/60)
B10: =IF(A10="","",MAX(1,MIN(Setup!$B$8,INT((A10-Setup!$B$6)/7)+1))) | G10: =IF(F10="","",F10/60)
B11: =IF(A11="","",MAX(1,MIN(Setup!$B$8,INT((A11-Setup!$B$6)/7)+1))) | G11: =IF(F11="","",F11/60)
B12: =IF(A12="","",MAX(1,MIN(Setup!$B$8,INT((A12-Setup!$B$6)/7)+1))) | G12: =IF(F12="","",F12/60)
B13: =IF(A13="","",MAX(1,MIN(Setup!$B$8,INT((A13-Setup!$B$6)/7)+1))) | G13: =IF(F13="","",F13/60)
B14: =IF(A14="","",MAX(1,MIN(Setup!$B$8,INT((A14-Setup!$B$6)/7)+1))) | G14: =IF(F14="","",F14/60)
B15: =IF(A15="","",MAX(1,MIN(Setup!$B$8,INT((A15-Setup!$B$6)/7)+1))) | G15: =IF(F15="","",F15/60)
B16: =IF(A16="","",MAX(1,MIN(Setup!$B$8,INT((A16-Setup!$B$6)/7)+1))) | G16: =IF(F16="","",F16/60)
... B204: =IF(A204="","",MAX(1,MIN(Setup!$B$8,INT((A204-Setup!$B$6)/7)+1))) | G204: =IF(F204="","",F204/60)

Sheet Milestones
A1: Phase Milestones | B1: Phase Milestones | C1: Phase Milestones | D1: Phase Milestones | E1: Phase Milestones | F1: Phase Milestones | G1: Phase Milestones | H1: Phase Milestones
A2: Phase Milestones | B2: Phase Milestones | C2: Phase Milestones | D2: Phase Milestones | E2: Phase Milestones | F2: Phase Milestones | G2: Phase Milestones | H2: Phase Milestones
A3: Mark a milestone complete only when its definition of done is supported by evidence. | B3: Mark a milestone complete only when its definition of done is supported by evidence. | C3: Mark a milestone complete only when its definition of done is supported by evidence. | D3: Mark a milestone complete only when its definition of done is supported by evidence. | E3: Mark a milestone complete only when its definition of done is supported by evidence. | F3: Mark a milestone complete only when its definition of done is supported by evidence. | G3: Mark a milestone complete only when its definition of done is supported by evidence. | H3: Mark a milestone complete only when its definition of done is supported by evidence.
A4: ID | B4: Target Week | C4: Milestone | D4: Definition of Done | E4: Status | F4: Completion | G4: Evidence / Link | H4: Review Notes
A5: M1 | B5: 1 | C5: Normalized data model | D5: Inventory and orders ERD includes keys, cardinality, constraints and correct data types | E5: Not Started | F5: =IF(E5="Completed",1,IF(E5="In Progress",0.5,IF(E5="Blocked",0.25,0))) -> 0
A6: M2 | B6: 4 | C6: Oracle SQL foundation | D6: Working schema and at least 40 correct queries including joins, subqueries, transactions and analytics | E6: Not Started | F6: =IF(E6="Completed",1,IF(E6="In Progress",0.5,IF(E6="Blocked",0.25,0))) -> 0
A7: M3 | B7: 8 | C7: PL/SQL fundamentals module | D7: Procedures and functions implement a small business flow with meaningful exception handling | E7: Not Started | F7: =IF(E7="Completed",1,IF(E7="In Progress",0.5,IF(E7="Blocked",0.25,0))) -> 0
A8: M4 | B8: 12 | C8: Package-based business API | D8: Public package specification hides implementation; triggers remain focused; errors retain diagnostic context | E8: Not Started | F8: =IF(E8="Completed",1,IF(E8="In Progress",0.5,IF(E8="Blocked",0.25,0))) -> 0
A9: M5 | B9: 16 | C9: Enterprise PL/SQL module | D9: Concurrency, dynamic SQL, rights, scheduled job and one data integration are demonstrated safely | E9: Not Started | F9: =IF(E9="Completed",1,IF(E9="In Progress",0.5,IF(E9="Blocked",0.25,0))) -> 0
A10: M6 | B10: 20 | C10: Production-quality module | D10: Measured tuning, automated tests, instrumentation and repeatable source-controlled deployment are complete | E10: Not Started | F10: =IF(E10="Completed",1,IF(E10="In Progress",0.5,IF(E10="Blocked",0.25,0))) -> 0
A11: M7 | B11: 22 | C11: Secure APEX integration | D11: APEX calls packaged APIs and correctly uses session state, validation, authorization, escaping and debug | E11: Not Started | F11: =IF(E11="Completed",1,IF(E11="In Progress",0.5,IF(E11="Blocked",0.25,0))) -> 0
A12: M8 | B12: 26 | C12: Portfolio capstone | D12: Application passes tests, security and performance review and can be installed in a clean environment | E12: Not Started | F12: =IF(E12="Completed",1,IF(E12="In Progress",0.5,IF(E12="Blocked",0.25,0))) -> 0

Sheet Capstone
A1: Capstone Feature Checklist | B1: Capstone Feature Checklist | C1: Capstone Feature Checklist | D1: Capstone Feature Checklist | E1: Capstone Feature Checklist | F1: Capstone Feature Checklist | G1: Capstone Feature Checklist | H1: Capstone Feature Checklist
A2: Capstone Feature Checklist | B2: Capstone Feature Checklist | C2: Capstone Feature Checklist | D2: Capstone Feature Checklist | E2: Capstone Feature Checklist | F2: Capstone Feature Checklist | G2: Capstone Feature Checklist | H2: Capstone Feature Checklist
A3: This is the portfolio proof that converts roadmap knowledge into professional APEX and PL/SQL capability. | B3: This is the portfolio proof that converts roadmap knowledge into professional APEX and PL/SQL capability. | C3: This is the portfolio proof that converts roadmap knowledge into professional APEX and PL/SQL capability. | D3: This is the portfolio proof that converts roadmap knowledge into professional APEX and PL/SQL capability. | E3: This is the portfolio proof that converts roadmap knowledge into professional APEX and PL/SQL capability. | F3: This is the portfolio proof that converts roadmap knowledge into professional APEX and PL/SQL capability. | G3: This is the portfolio proof that converts roadmap knowledge into professional APEX and PL/SQL capability. | H3: This is the portfolio proof that converts roadmap knowledge into professional APEX and PL/SQL capability.
A4: Category | B4: Feature | C4: Target Week | D4: Definition of Done | E4: Status | F4: Completion | G4: Evidence / Link | H4: Notes
A5: Data Model | B5: Products, categories and suppliers | C5: 24 | D5: Normalized tables, constraints and working maintenance pages | E5: Not Started | F5: =IF(E5="Completed",1,IF(E5="In Progress",0.5,IF(E5="Blocked",0.25,0))) -> 0
A6: Data Model | B6: Warehouses and stock movements | C6: 24 | D6: All stock changes are recorded as auditable movements | E6: Not Started | F6: =IF(E6="Completed",1,IF(E6="In Progress",0.5,IF(E6="Blocked",0.25,0))) -> 0
A7: Orders | B7: Order header and lines | C7: 24 | D7: Master-detail flow calculates totals and validates line data | E7: Not Started | F7: =IF(E7="Completed",1,IF(E7="In Progress",0.5,IF(E7="Blocked",0.25,0))) -> 0
A8: Orders | B8: Order status workflow | C8: 24 | D8: Only valid state transitions are permitted by the package API | E8: Not Started | F8: =IF(E8="Completed",1,IF(E8="In Progress",0.5,IF(E8="Blocked",0.25,0))) -> 0
A9: Concurrency | B9: Stock reservation | C9: 24 | D9: Two sessions cannot reserve the same final quantity | E9: Not Started | F9: =IF(E9="Completed",1,IF(E9="In Progress",0.5,IF(E9="Blocked",0.25,0))) -> 0
A10: Architecture | B10: Public package APIs | C10: 24 | D10: APEX pages call product_api, inventory_api and order_api | E10: Not Started | F10: =IF(E10="Completed",1,IF(E10="In Progress",0.5,IF(E10="Blocked",0.25,0))) -> 0
A11: Errors | B11: Error and audit logging | C11: 24 | D11: Unexpected errors retain stack and backtrace; business errors are user-safe | E11: Not Started | F11: =IF(E11="Completed",1,IF(E11="In Progress",0.5,IF(E11="Blocked",0.25,0))) -> 0
A12: Testing | B12: utPLSQL package tests | C12: 24 | D12: Core happy paths, boundaries and expected failures are automated | E12: Not Started | F12: =IF(E12="Completed",1,IF(E12="In Progress",0.5,IF(E12="Blocked",0.25,0))) -> 0
A13: Security | B13: Authentication and authorization | C13: 25 | D13: Admin, manager and user roles have verified permissions | E13: Not Started | F13: =IF(E13="Completed",1,IF(E13="In Progress",0.5,IF(E13="Blocked",0.25,0))) -> 0
A14: Security | B14: Session state and output security | C14: 25 | D14: Sensitive items use protection and dynamic output is escaped | E14: Not Started | F14: =IF(E14="Completed",1,IF(E14="In Progress",0.5,IF(E14="Blocked",0.25,0))) -> 0
A15: Reporting | B15: Operational dashboard | C15: 25 | D15: Shows sales, inventory, low stock and order-status KPIs | E15: Not Started | F15: =IF(E15="Completed",1,IF(E15="In Progress",0.5,IF(E15="Blocked",0.25,0))) -> 0
A16: Reporting | B16: Analytic SQL reports | C16: 25 | D16: Includes ranking, running totals and period comparison | E16: Not Started | F16: =IF(E16="Completed",1,IF(E16="In Progress",0.5,IF(E16="Blocked",0.25,0))) -> 0
... A24: Portfolio | B24: README, ERD, screenshots and demo | C24: 26 | D24: A reviewer can understand, install and evaluate the application | E24: Not Started | F24: =IF(E24="Completed",1,IF(E24="In Progress",0.5,IF(E24="Blocked",0.25,0))) -> 0

Sheet Setup
A1: PL/SQL Roadmap Tracker — Setup | B1: PL/SQL Roadmap Tracker — Setup | C1: PL/SQL Roadmap Tracker — Setup | D1: PL/SQL Roadmap Tracker — Setup | E1: PL/SQL Roadmap Tracker — Setup | F1: PL/SQL Roadmap Tracker — Setup
A2: PL/SQL Roadmap Tracker — Setup | B2: PL/SQL Roadmap Tracker — Setup | C2: PL/SQL Roadmap Tracker — Setup | D2: PL/SQL Roadmap Tracker — Setup | E2: PL/SQL Roadmap Tracker — Setup | F2: PL/SQL Roadmap Tracker — Setup
A3: Edit the blue input cells. All dates, targets and dashboard metrics update automatically. | B3: Edit the blue input cells. All dates, targets and dashboard metrics update automatically. | C3: Edit the blue input cells. All dates, targets and dashboard metrics update automatically. | D3: Edit the blue input cells. All dates, targets and dashboard metrics update automatically. | E3: Edit the blue input cells. All dates, targets and dashboard metrics update automatically. | F3: Edit the blue input cells. All dates, targets and dashboard metrics update automatically.
A5: Setting | B5: Value | C5: How it is used
A6: Roadmap start date | B6: 46223 | C6: Week 1 begins on this date
A7: Target hours per week | B7: 8 | C7: Copied into the weekly plan
A8: Roadmap length (weeks) | B8: 26 | C8: Used by current-week calculations
A10: Status | B10: Progress weight | C10: Meaning
A11: Not Started | B11: 0 | C11: No meaningful work recorded
A12: In Progress | B12: 0.5 | C12: Learning or practice has started
A13: Blocked | B13: 0.25 | C13: Started but a blocker needs attention
A14: Completed | B14: 1 | C14: Exit evidence is available
A16: Official resource | B16: URL | C16: Use
A17: PL/SQL Language Reference 26ai | B17: https://docs.oracle.com/en/database/oracle/oracle-database/26/lnpls/ | C17: Primary language reference
A18: SQL Language Reference 26ai | B18: https://docs.oracle.com/en/database/oracle/oracle-database/26/sqlrf/ | C18: Oracle SQL syntax and behavior
A19: APEX App Builder Guide 26.1 | B19: https://docs.oracle.com/en/database/oracle/apex/26.1/htmdb/ | C19: APEX lifecycle, session state and security
A20: APEX API Reference 26.1 | B20: https://docs.oracle.com/en/database/oracle/apex/26.1/aeapi/ | C20: APEX PL/SQL APIs
A21: Oracle FreeSQL | B21: https://www.oracle.com/database/technologies/oracle-free-sql/ | C21: Browser-based Oracle practice
A22: utPLSQL | B22: https://www.utplsql.org/utPLSQL/latest/ | C22: Automated PL/SQL testing
